bwd/__init__.py
bwd/bwd.py
bwd/bwd_random.py
bwd/exceptions.py
bwd/multi_bwd.py
bwd/online.py
bwd/serialization.py
bwd-0.2.0.dist-info/METADATA
bwd-0.2.0.dist-info/WHEEL
bwd-0.2.0.dist-info/licenses/LICENSE
bwd-0.2.0.dist-info/RECORD
