Metadata-Version: 2.4
Name: bwd
Version: 0.2.0
Summary: A clean implementation of the Balancing Walk Design for online experimental design from Arbour, Dimmery, Mai and Rao (2022)
License: Apache-2.0
License-File: LICENSE
Keywords: causal inference,experimentation,ab testing
Author: Drew Dimmery
Author-email: drew.dimmery@gmail.com
Requires-Python: >=3.12,<4.0
Classifier: License :: OSI Approved :: Apache Software License
Classifier: Programming Language :: Python :: 3
Classifier: Programming Language :: Python :: 3.12
Classifier: Programming Language :: Python :: 3.13
Classifier: Programming Language :: Python :: 3.14
Requires-Dist: numpy (>=1.22)
Project-URL: Homepage, https://ddimmery.github.io/balancer-package/
Project-URL: Repository, https://github.com/ddimmery/balancer-package
